LICENSE
MANIFEST.in
README.md
pyproject.toml
fragile_nes_py.egg-info/PKG-INFO
fragile_nes_py.egg-info/SOURCES.txt
fragile_nes_py.egg-info/dependency_links.txt
fragile_nes_py.egg-info/entry_points.txt
fragile_nes_py.egg-info/requires.txt
fragile_nes_py.egg-info/top_level.txt
nes_py/__init__.py
nes_py/_image_viewer.py
nes_py/_rom.py
nes_py/nes_env.py
nes_py/app/__init__.py
nes_py/app/cli.py
nes_py/app/play_human.py
nes_py/app/play_random.py
nes_py/nes/SConstruct
nes_py/nes/include/cartridge.hpp
nes_py/nes/include/common.hpp
nes_py/nes/include/controller.hpp
nes_py/nes/include/cpu.hpp
nes_py/nes/include/cpu_opcodes.hpp
nes_py/nes/include/emulator.hpp
nes_py/nes/include/log.hpp
nes_py/nes/include/main_bus.hpp
nes_py/nes/include/mapper.hpp
nes_py/nes/include/mapper_factory.hpp
nes_py/nes/include/palette.hpp
nes_py/nes/include/picture_bus.hpp
nes_py/nes/include/ppu.hpp
nes_py/nes/include/mappers/mapper_CNROM.hpp
nes_py/nes/include/mappers/mapper_NROM.hpp
nes_py/nes/include/mappers/mapper_SxROM.hpp
nes_py/nes/include/mappers/mapper_UxROM.hpp
nes_py/nes/src/cartridge.cpp
nes_py/nes/src/controller.cpp
nes_py/nes/src/cpu.cpp
nes_py/nes/src/emulator.cpp
nes_py/nes/src/lib_nes_env.cpp
nes_py/nes/src/main_bus.cpp
nes_py/nes/src/picture_bus.cpp
nes_py/nes/src/ppu.cpp
nes_py/nes/src/mappers/mapper_CNROM.cpp
nes_py/nes/src/mappers/mapper_NROM.cpp
nes_py/nes/src/mappers/mapper_SxROM.cpp
nes_py/nes/src/mappers/mapper_UxROM.cpp
nes_py/tests/__init__.py
nes_py/tests/rom_file_abs_path.py
nes_py/tests/test_multiple_makes.py
nes_py/tests/test_nes_env.py
nes_py/tests/test_rom.py
nes_py/wrappers/__init__.py
nes_py/wrappers/joypad_space.py